{"is_source_file": true, "format": "Dart", "description": "A Flutter widget implementing a login page with form validation, user authentication, and navigation functionalities.", "external_files": ["../../app_theme.dart", "../../providers/auth_provider.dart", "../../utils/validators.dart"], "external_methods": ["Validators.validateEmail", "Validators.validatePassword", "context.read", "Navigator.of", "ScaffoldMessenger.of"], "published": ["LoginPage"], "classes": [{"name": "LoginPage", "description": "A StatefulWidget representing the login page interface."}, {"name": "_LoginPageState", "description": "State class managing the login form state, input handling, and user login process."}], "methods": [{"name": "_submit", "description": "Handles form validation, initiates login via AuthProvider, manages loading state, and navigates upon success or failure."}, {"name": "build", "description": "Builds the widget tree for the login page UI."}], "calls": ["formKey.currentState?.validate", "context.read<AuthProvider>().login", "Navigator.of(context).pushNamedAndRemoveUntil", "ScaffoldMessenger.of(context).showSnackBar"], "search-terms": ["Flutter login page", "AuthProvider login", "form validation", "Navigator routing", "Checkbox login form"], "state": 2, "file_id": 36, "knowledge_revision": 74, "git_revision": "", "hash": "f6187e62e91a26a9044fd558f28a5eab", "format-version": 4, "code-base-name": "pickleball_frontend", "filename": "pickleball_frontend/lib/src/pages/auth/login_page.dart", "revision_history": [{"74": ""}]}